LICENSE
MANIFEST.in
README.rst
setup.cfg
setup.py
html5validator/__init__.py
html5validator/cli.py
html5validator/validator.py
html5validator.egg-info/PKG-INFO
html5validator.egg-info/SOURCES.txt
html5validator.egg-info/dependency_links.txt
html5validator.egg-info/entry_points.txt
html5validator.egg-info/requires.txt
html5validator.egg-info/top_level.txt
html5validator/tests/__init__.py
html5validator/tests/test_simple.py
vnujar/__init__.py
vnujar/vnu.jar